[{"id":41,"title":"Futuristic Chic High-Heel Boots","price":36,"description":"Elevate your style with our cutting-edge high-heel boots that blend bold design with avant-garde aesthetics. These boots feature a unique color-block heel, a sleek silhouette, and a versatile light grey finish that pairs easily with any cutting-edge outfit. Crafted for the fashion-forward individual, these boots are sure to make a statement.","images":["https://i.imgur.com/HqYqLnW.jpeg","https://i.imgur.com/RlDGnZw.jpeg","https://i.imgur.com/qa0O6fg.jpeg"],"creationAt":"2024-11-01T23:00:57.000Z","updatedAt":"2024-11-01T23:00:57.000Z","category":{"id":4,"name":"Shoes","image":"https://i.imgur.com/qNOjJje.jpeg","creationAt":"2024-11-01T23:00:57.000Z","updatedAt":"2024-11-01T23:00:57.000Z"}},{"id":44,"title":"Classic Blue Suede Casual Shoes","price":39,"description":"Step into comfort with our Classic Blue Suede Casual Shoes, perfect for everyday wear. These shoes feature a stylish blue suede upper, durable rubber soles for superior traction, and classic lace-up fronts for a snug fit. The sleek design pairs well with both jeans and chinos, making them a versatile addition to any wardrobe.","images":["https://i.imgur.com/sC0ztOB.jpeg","https://i.imgur.com/Jf9DL9R.jpeg","https://i.imgur.com/R1IN95T.jpeg"],"creationAt":"2024-11-01T23:00:58.000Z","updatedAt":"2024-11-01T23:00:58.000Z","category":{"id":4,"name":"Shoes","image":"https://i.imgur.com/qNOjJje.jpeg","creationAt":"2024-11-01T23:00:57.000Z","updatedAt":"2024-11-01T23:00:57.000Z"}},{"id":45,"title":"Sleek Futuristic Electric Bicycle","price":22,"description":"This modern electric bicycle combines style and efficiency with its unique design and top-notch performance features. Equipped with a durable frame, enhanced battery life, and integrated tech capabilities, it's perfect for the eco-conscious commuter looking to navigate the city with ease.","images":["https://i.imgur.com/BG8J0Fj.jpg","https://i.imgur.com/ujHBpCX.jpg","https://i.imgur.com/WHeVL9H.jpg"],"creationAt":"2024-11-01T23:00:58.000Z","updatedAt":"2024-11-01T23:00:58.000Z","category":{"id":5,"name":"Miscellaneous","image":"https://i.imgur.com/BG8J0Fj.jpg","creationAt":"2024-11-01T23:00:57.000Z","updatedAt":"2024-11-01T23:00:57.000Z"}},{"id":46,"title":"Sleek All-Terrain Go-Kart","price":37,"description":"Experience the thrill of outdoor adventures with our Sleek All-Terrain Go-Kart, featuring a durable frame, comfortable racing seat, and robust, large-tread tires perfect for handling a variety of terrains. Designed for fun-seekers of all ages, this go-kart is an ideal choice for backyard racing or exploring local trails.","images":["https://i.imgur.com/Ex5x3IU.jpg","https://i.imgur.com/z7wAQwe.jpg","https://i.imgur.com/kc0Dj9S.jpg"],"creationAt":"2024-11-01T23:00:58.000Z","updatedAt":"2024-11-01T23:00:58.000Z","category":{"id":5,"name":"Miscellaneous","image":"https://i.imgur.com/BG8J0Fj.jpg","creationAt":"2024-11-01T23:00:57.000Z","updatedAt":"2024-11-01T23:00:57.000Z"}},{"id":47,"title":"Radiant Citrus Eau de Parfum","price":73,"description":"Indulge in the essence of summer with this vibrant citrus-scented Eau de Parfum. Encased in a sleek glass bottle with a bold orange cap, this fragrance embodies freshness and elegance. Perfect for daily wear, it's an olfactory delight that leaves a lasting, zesty impression.","images":["https://i.imgur.com/xPDwUb3.jpg","https://i.imgur.com/3rfp691.jpg","https://i.imgur.com/kG05a29.jpg"],"creationAt":"2024-11-01T23:00:58.000Z","updatedAt":"2024-11-01T23:00:58.000Z","category":{"id":5,"name":"Miscellaneous","image":"https://i.imgur.com/BG8J0Fj.jpg","creationAt":"2024-11-01T23:00:57.000Z","updatedAt":"2024-11-01T23:00:57.000Z"}},{"id":49,"title":"Chic Transparent Fashion Handbag","price":61,"description":"Elevate your style with our Chic Transparent Fashion Handbag, perfect for showcasing your essentials with a clear, modern edge. This trendy accessory features durable acrylic construction, luxe gold-tone hardware, and an elegant chain strap. Its compact size ensures you can carry your day-to-day items with ease and sophistication.","images":["https://i.imgur.com/Lqaqz59.jpg","https://i.imgur.com/uSqWK0m.jpg","https://i.imgur.com/atWACf1.jpg"],"creationAt":"2024-11-01T23:00:58.000Z","updatedAt":"2024-11-01T23:00:58.000Z","category":{"id":5,"name":"Miscellaneous","image":"https://i.imgur.com/BG8J0Fj.jpg","creationAt":"2024-11-01T23:00:57.000Z","updatedAt":"2024-11-01T23:00:57.000Z"}},{"id":69,"title":"New Product","price":10,"description":"A description","images":["[\"https://placeimg.com/640/480/any\"]"],"creationAt":"2024-11-02T04:36:11.000Z","updatedAt":"2024-11-02T04:36:11.000Z","category":{"id":1,"name":"Clothes","image":"https://i.imgur.com/QkIa5tT.jpeg","creationAt":"2024-11-01T23:00:57.000Z","updatedAt":"2024-11-01T23:00:57.000Z"}},{"id":70,"title":"New Product","price":10,"description":"A description","images":["[\"https://placeimg.com/640/480/any\"]"],"creationAt":"2024-11-02T04:45:53.000Z","updatedAt":"2024-11-02T04:45:53.000Z","category":{"id":1,"name":"Clothes","image":"https://i.imgur.com/QkIa5tT.jpeg","creationAt":"2024-11-01T23:00:57.000Z","updatedAt":"2024-11-01T23:00:57.000Z"}},{"id":71,"title":"New Product","price":10,"description":"A description","images":["[\"https://placeimg.com/640/480/any\"]"],"creationAt":"2024-11-02T04:52:27.000Z","updatedAt":"2024-11-02T04:52:27.000Z","category":{"id":1,"name":"Clothes","image":"https://i.imgur.com/QkIa5tT.jpeg","creationAt":"2024-11-01T23:00:57.000Z","updatedAt":"2024-11-01T23:00:57.000Z"}},{"id":72,"title":"New Product","price":10,"description":"A description","images":["[\"https://placeimg.com/640/480/any\"]"],"creationAt":"2024-11-02T04:58:54.000Z","updatedAt":"2024-11-02T04:58:54.000Z","category":{"id":1,"name":"Clothes","image":"https://i.imgur.com/QkIa5tT.jpeg","creationAt":"2024-11-01T23:00:57.000Z","updatedAt":"2024-11-01T23:00:57.000Z"}},{"id":74,"title":"New Product","price":10,"description":"A description","images":["[\"https://placeimg.com/640/480/any\"]"],"creationAt":"2024-11-02T05:31:13.000Z","updatedAt":"2024-11-02T05:31:13.000Z","category":{"id":1,"name":"Clothes","image":"https://i.imgur.com/QkIa5tT.jpeg","creationAt":"2024-11-01T23:00:57.000Z","updatedAt":"2024-11-01T23:00:57.000Z"}},{"id":75,"title":"New Product","price":10,"description":"A description","images":["[\"https://placeimg.com/640/480/any\"]"],"creationAt":"2024-11-02T05:39:11.000Z","updatedAt":"2024-11-02T05:39:11.000Z","category":{"id":1,"name":"Clothes","image":"https://i.imgur.com/QkIa5tT.jpeg","creationAt":"2024-11-01T23:00:57.000Z","updatedAt":"2024-11-01T23:00:57.000Z"}},{"id":78,"title":"New Product","price":10,"description":"A description","images":["[\"https://placeimg.com/640/480/any\"]"],"creationAt":"2024-11-02T05:53:46.000Z","updatedAt":"2024-11-02T05:53:46.000Z","category":{"id":1,"name":"Clothes","image":"https://i.imgur.com/QkIa5tT.jpeg","creationAt":"2024-11-01T23:00:57.000Z","updatedAt":"2024-11-01T23:00:57.000Z"}},{"id":103,"title":"New Product","price":10,"description":"A description","images":["[\"https://placeimg.com/640/480/any\"]"],"creationAt":"2024-11-02T07:53:01.000Z","updatedAt":"2024-11-02T07:53:01.000Z","category":{"id":1,"name":"Clothes","image":"https://i.imgur.com/QkIa5tT.jpeg","creationAt":"2024-11-01T23:00:57.000Z","updatedAt":"2024-11-01T23:00:57.000Z"}},{"id":104,"title":"New Product","price":10,"description":"A description","images":["[\"https://placeimg.com/640/480/any\"]"],"creationAt":"2024-11-02T07:59:37.000Z","updatedAt":"2024-11-02T07:59:37.000Z","category":{"id":1,"name":"Clothes","image":"https://i.imgur.com/QkIa5tT.jpeg","creationAt":"2024-11-01T23:00:57.000Z","updatedAt":"2024-11-01T23:00:57.000Z"}},{"id":105,"title":"New Product","price":10,"description":"A description","images":["[\"https://placeimg.com/640/480/any\"]"],"creationAt":"2024-11-02T08:21:27.000Z","updatedAt":"2024-11-02T08:21:27.000Z","category":{"id":1,"name":"Clothes","image":"https://i.imgur.com/QkIa5tT.jpeg","creationAt":"2024-11-01T23:00:57.000Z","updatedAt":"2024-11-01T23:00:57.000Z"}},{"id":106,"title":"New Product","price":10,"description":"A description","images":["[\"https://placeimg.com/640/480/any\"]"],"creationAt":"2024-11-02T08:35:38.000Z","updatedAt":"2024-11-02T08:35:38.000Z","category":{"id":1,"name":"Clothes","image":"https://i.imgur.com/QkIa5tT.jpeg","creationAt":"2024-11-01T23:00:57.000Z","updatedAt":"2024-11-01T23:00:57.000Z"}},{"id":107,"title":"gsdgsd","price":2424,"description":"gdsgsd","images":["[\"https://idnayka.ru/wp-content/uploads/2021/01/konf-2020.png\"]"],"creationAt":"2024-11-02T08:42:41.000Z","updatedAt":"2024-11-02T08:42:41.000Z","category":{"id":2,"name":"Electronics","image":"https://i.imgur.com/ZANVnHE.jpeg","creationAt":"2024-11-01T23:00:57.000Z","updatedAt":"2024-11-01T23:00:57.000Z"}},{"id":109,"title":"New Product","price":10,"description":"A description","images":["[\"https://placeimg.com/640/480/any\"]"],"creationAt":"2024-11-02T08:44:54.000Z","updatedAt":"2024-11-02T08:44:54.000Z","category":{"id":1,"name":"Clothes","image":"https://i.imgur.com/QkIa5tT.jpeg","creationAt":"2024-11-01T23:00:57.000Z","updatedAt":"2024-11-01T23:00:57.000Z"}},{"id":111,"title":"New Product","price":10,"description":"A description","images":["[\"https://placeimg.com/640/480/any\"]"],"creationAt":"2024-11-02T08:51:16.000Z","updatedAt":"2024-11-02T08:51:16.000Z","category":{"id":1,"name":"Clothes","image":"https://i.imgur.com/QkIa5tT.jpeg","creationAt":"2024-11-01T23:00:57.000Z","updatedAt":"2024-11-01T23:00:57.000Z"}},{"id":112,"title":"New Product","price":10,"description":"A description","images":["[\"https://placeimg.com/640/480/any\"]"],"creationAt":"2024-11-02T08:57:38.000Z","updatedAt":"2024-11-02T08:57:38.000Z","category":{"id":1,"name":"Clothes","image":"https://i.imgur.com/QkIa5tT.jpeg","creationAt":"2024-11-01T23:00:57.000Z","updatedAt":"2024-11-01T23:00:57.000Z"}},{"id":113,"title":"New Product","price":10,"description":"A description","images":["[\"https://placeimg.com/640/480/any\"]"],"creationAt":"2024-11-02T09:12:59.000Z","updatedAt":"2024-11-02T09:12:59.000Z","category":{"id":1,"name":"Clothes","image":"https://i.imgur.com/QkIa5tT.jpeg","creationAt":"2024-11-01T23:00:57.000Z","updatedAt":"2024-11-01T23:00:57.000Z"}},{"id":114,"title":"New Product","price":10,"description":"A description","images":["[\"https://placeimg.com/640/480/any\"]"],"creationAt":"2024-11-02T09:27:19.000Z","updatedAt":"2024-11-02T09:27:19.000Z","category":{"id":1,"name":"Clothes","image":"https://i.imgur.com/QkIa5tT.jpeg","creationAt":"2024-11-01T23:00:57.000Z","updatedAt":"2024-11-01T23:00:57.000Z"}},{"id":115,"title":"New Product","price":10,"description":"A description","images":["[\"https://placeimg.com/640/480/any\"]"],"creationAt":"2024-11-02T09:35:13.000Z","updatedAt":"2024-11-02T09:35:13.000Z","category":{"id":1,"name":"Clothes","image":"https://i.imgur.com/QkIa5tT.jpeg","creationAt":"2024-11-01T23:00:57.000Z","updatedAt":"2024-11-01T23:00:57.000Z"}},{"id":116,"title":"New Product","price":10,"description":"A description","images":["[\"https://placeimg.com/640/480/any\"]"],"creationAt":"2024-11-02T09:41:38.000Z","updatedAt":"2024-11-02T09:41:38.000Z","category":{"id":1,"name":"Clothes","image":"https://i.imgur.com/QkIa5tT.jpeg","creationAt":"2024-11-01T23:00:57.000Z","updatedAt":"2024-11-01T23:00:57.000Z"}},{"id":117,"title":"New Product","price":10,"description":"A description","images":["[\"https://placeimg.com/640/480/any\"]"],"creationAt":"2024-11-02T09:48:15.000Z","updatedAt":"2024-11-02T09:48:15.000Z","category":{"id":1,"name":"Clothes","image":"https://i.imgur.com/QkIa5tT.jpeg","creationAt":"2024-11-01T23:00:57.000Z","updatedAt":"2024-11-01T23:00:57.000Z"}},{"id":118,"title":"New Product","price":10,"description":"A description","images":["[\"https://placeimg.com/640/480/any\"]"],"creationAt":"2024-11-02T09:54:50.000Z","updatedAt":"2024-11-02T09:54:50.000Z","category":{"id":1,"name":"Clothes","image":"https://i.imgur.com/QkIa5tT.jpeg","creationAt":"2024-11-01T23:00:57.000Z","updatedAt":"2024-11-01T23:00:57.000Z"}},{"id":119,"title":"New Product","price":10,"description":"A description","images":["[\"https://placeimg.com/640/480/any\"]"],"creationAt":"2024-11-02T10:07:57.000Z","updatedAt":"2024-11-02T10:07:57.000Z","category":{"id":1,"name":"Clothes","image":"https://i.imgur.com/QkIa5tT.jpeg","creationAt":"2024-11-01T23:00:57.000Z","updatedAt":"2024-11-01T23:00:57.000Z"}},{"id":122,"title":"New Product","price":10,"description":"A description","images":["[\"https://placeimg.com/640/480/any\"]"],"creationAt":"2024-11-02T10:38:32.000Z","updatedAt":"2024-11-02T10:38:32.000Z","category":{"id":1,"name":"Clothes","image":"https://i.imgur.com/QkIa5tT.jpeg","creationAt":"2024-11-01T23:00:57.000Z","updatedAt":"2024-11-01T23:00:57.000Z"}},{"id":123,"title":"New Product","price":10,"description":"A description","images":["[\"https://placeimg.com/640/480/any\"]"],"creationAt":"2024-11-02T10:45:05.000Z","updatedAt":"2024-11-02T10:45:05.000Z","category":{"id":1,"name":"Clothes","image":"https://i.imgur.com/QkIa5tT.jpeg","creationAt":"2024-11-01T23:00:57.000Z","updatedAt":"2024-11-01T23:00:57.000Z"}},{"id":127,"title":"212","price":212,"description":"A description","images":["[\"https://placeimg.com/640/480/any\"]"],"creationAt":"2024-11-02T10:55:50.000Z","updatedAt":"2024-11-02T10:55:50.000Z","category":{"id":1,"name":"Clothes","image":"https://i.imgur.com/QkIa5tT.jpeg","creationAt":"2024-11-01T23:00:57.000Z","updatedAt":"2024-11-01T23:00:57.000Z"}},{"id":133,"title":"Mobile Phones","price":10,"description":"A description","images":["[\"https://placeimg.com/640/480/any\"]"],"creationAt":"2024-11-02T11:03:10.000Z","updatedAt":"2024-11-02T11:03:10.000Z","category":{"id":1,"name":"Clothes","image":"https://i.imgur.com/QkIa5tT.jpeg","creationAt":"2024-11-01T23:00:57.000Z","updatedAt":"2024-11-01T23:00:57.000Z"}},{"id":134,"title":"New Product R","price":1034,"description":"A description","images":["[\"https://placeimg.com/640/480/any\"]"],"creationAt":"2024-11-02T11:10:51.000Z","updatedAt":"2024-11-02T11:10:51.000Z","category":{"id":1,"name":"Clothes","image":"https://i.imgur.com/QkIa5tT.jpeg","creationAt":"2024-11-01T23:00:57.000Z","updatedAt":"2024-11-01T23:00:57.000Z"}},{"id":135,"title":"New Product R","price":1034,"description":"A description","images":["[\"https://placeimg.com/640/480/any\"]"],"creationAt":"2024-11-02T11:10:52.000Z","updatedAt":"2024-11-02T11:10:52.000Z","category":{"id":1,"name":"Clothes","image":"https://i.imgur.com/QkIa5tT.jpeg","creationAt":"2024-11-01T23:00:57.000Z","updatedAt":"2024-11-01T23:00:57.000Z"}},{"id":136,"title":"New Product R","price":1034,"description":"A description","images":["[\"https://placeimg.com/640/480/any\"]"],"creationAt":"2024-11-02T11:10:52.000Z","updatedAt":"2024-11-02T11:10:52.000Z","category":{"id":1,"name":"Clothes","image":"https://i.imgur.com/QkIa5tT.jpeg","creationAt":"2024-11-01T23:00:57.000Z","updatedAt":"2024-11-01T23:00:57.000Z"}},{"id":137,"title":"New Product","price":10,"description":"A description","images":["[\"https://placeimg.com/640/480/any\"]"],"creationAt":"2024-11-02T11:11:55.000Z","updatedAt":"2024-11-02T11:11:55.000Z","category":{"id":1,"name":"Clothes","image":"https://i.imgur.com/QkIa5tT.jpeg","creationAt":"2024-11-01T23:00:57.000Z","updatedAt":"2024-11-01T23:00:57.000Z"}},{"id":138,"title":"New Product","price":10,"description":"A description","images":["[\"https://placeimg.com/640/480/any\"]"],"creationAt":"2024-11-02T11:22:08.000Z","updatedAt":"2024-11-02T11:22:08.000Z","category":{"id":1,"name":"Clothes","image":"https://i.imgur.com/QkIa5tT.jpeg","creationAt":"2024-11-01T23:00:57.000Z","updatedAt":"2024-11-01T23:00:57.000Z"}},{"id":139,"title":"New Product","price":10,"description":"A description","images":["[\"https://placeimg.com/640/480/any\"]"],"creationAt":"2024-11-02T11:28:32.000Z","updatedAt":"2024-11-02T11:28:32.000Z","category":{"id":1,"name":"Clothes","image":"https://i.imgur.com/QkIa5tT.jpeg","creationAt":"2024-11-01T23:00:57.000Z","updatedAt":"2024-11-01T23:00:57.000Z"}},{"id":140,"title":"New Product","price":10,"description":"A description","images":["[\"https://placeimg.com/640/480/any\"]"],"creationAt":"2024-11-02T11:36:17.000Z","updatedAt":"2024-11-02T11:36:17.000Z","category":{"id":1,"name":"Clothes","image":"https://i.imgur.com/QkIa5tT.jpeg","creationAt":"2024-11-01T23:00:57.000Z","updatedAt":"2024-11-01T23:00:57.000Z"}},{"id":141,"title":"New Product R","price":1034,"description":"A description","images":["[\"https://placeimg.com/640/480/any\"]"],"creationAt":"2024-11-02T11:37:23.000Z","updatedAt":"2024-11-02T11:37:23.000Z","category":{"id":1,"name":"Clothes","image":"https://i.imgur.com/QkIa5tT.jpeg","creationAt":"2024-11-01T23:00:57.000Z","updatedAt":"2024-11-01T23:00:57.000Z"}},{"id":142,"title":"New Product R","price":1034,"description":"A description","images":["[\"https://placeimg.com/640/480/any\"]"],"creationAt":"2024-11-02T11:37:24.000Z","updatedAt":"2024-11-02T11:37:24.000Z","category":{"id":1,"name":"Clothes","image":"https://i.imgur.com/QkIa5tT.jpeg","creationAt":"2024-11-01T23:00:57.000Z","updatedAt":"2024-11-01T23:00:57.000Z"}},{"id":143,"title":"New Product R","price":1034,"description":"A description","images":["[\"https://placeimg.com/640/480/any\"]"],"creationAt":"2024-11-02T11:37:25.000Z","updatedAt":"2024-11-02T11:37:25.000Z","category":{"id":1,"name":"Clothes","image":"https://i.imgur.com/QkIa5tT.jpeg","creationAt":"2024-11-01T23:00:57.000Z","updatedAt":"2024-11-01T23:00:57.000Z"}},{"id":144,"title":"New Product","price":10,"description":"A description","images":["[\"https://placeimg.com/640/480/any\"]"],"creationAt":"2024-11-02T11:42:50.000Z","updatedAt":"2024-11-02T11:42:50.000Z","category":{"id":1,"name":"Clothes","image":"https://i.imgur.com/QkIa5tT.jpeg","creationAt":"2024-11-01T23:00:57.000Z","updatedAt":"2024-11-01T23:00:57.000Z"}},{"id":145,"title":"New Product R","price":1034,"description":"A description","images":["[\"https://placeimg.com/640/480/any\"]"],"creationAt":"2024-11-02T11:44:50.000Z","updatedAt":"2024-11-02T11:44:50.000Z","category":{"id":1,"name":"Clothes","image":"https://i.imgur.com/QkIa5tT.jpeg","creationAt":"2024-11-01T23:00:57.000Z","updatedAt":"2024-11-01T23:00:57.000Z"}},{"id":146,"title":"New Product R","price":1034,"description":"A description","images":["[\"https://placeimg.com/640/480/any\"]"],"creationAt":"2024-11-02T11:44:51.000Z","updatedAt":"2024-11-02T11:44:51.000Z","category":{"id":1,"name":"Clothes","image":"https://i.imgur.com/QkIa5tT.jpeg","creationAt":"2024-11-01T23:00:57.000Z","updatedAt":"2024-11-01T23:00:57.000Z"}},{"id":147,"title":"New Product R","price":1034,"description":"A description","images":["[\"https://placeimg.com/640/480/any\"]"],"creationAt":"2024-11-02T11:44:52.000Z","updatedAt":"2024-11-02T11:44:52.000Z","category":{"id":1,"name":"Clothes","image":"https://i.imgur.com/QkIa5tT.jpeg","creationAt":"2024-11-01T23:00:57.000Z","updatedAt":"2024-11-01T23:00:57.000Z"}},{"id":148,"title":"New Product R","price":1034,"description":"A description","images":["[\"https://placeimg.com/640/480/any\"]"],"creationAt":"2024-11-02T11:48:19.000Z","updatedAt":"2024-11-02T11:48:19.000Z","category":{"id":1,"name":"Clothes","image":"https://i.imgur.com/QkIa5tT.jpeg","creationAt":"2024-11-01T23:00:57.000Z","updatedAt":"2024-11-01T23:00:57.000Z"}},{"id":149,"title":"New Product R","price":1034,"description":"A description","images":["[\"https://placeimg.com/640/480/any\"]"],"creationAt":"2024-11-02T11:48:20.000Z","updatedAt":"2024-11-02T11:48:20.000Z","category":{"id":1,"name":"Clothes","image":"https://i.imgur.com/QkIa5tT.jpeg","creationAt":"2024-11-01T23:00:57.000Z","updatedAt":"2024-11-01T23:00:57.000Z"}},{"id":150,"title":"New Product R","price":1034,"description":"A description","images":["[\"https://placeimg.com/640/480/any\"]"],"creationAt":"2024-11-02T11:48:21.000Z","updatedAt":"2024-11-02T11:48:21.000Z","category":{"id":1,"name":"Clothes","image":"https://i.imgur.com/QkIa5tT.jpeg","creationAt":"2024-11-01T23:00:57.000Z","updatedAt":"2024-11-01T23:00:57.000Z"}},{"id":151,"title":"New Product R","price":1034,"description":"A description","images":["[\"https://placeimg.com/640/480/any\"]"],"creationAt":"2024-11-02T11:48:22.000Z","updatedAt":"2024-11-02T11:48:22.000Z","category":{"id":1,"name":"Clothes","image":"https://i.imgur.com/QkIa5tT.jpeg","creationAt":"2024-11-01T23:00:57.000Z","updatedAt":"2024-11-01T23:00:57.000Z"}},{"id":152,"title":"New Product R","price":1034,"description":"A description","images":["[\"https://placeimg.com/640/480/any\"]"],"creationAt":"2024-11-02T11:49:20.000Z","updatedAt":"2024-11-02T11:49:20.000Z","category":{"id":1,"name":"Clothes","image":"https://i.imgur.com/QkIa5tT.jpeg","creationAt":"2024-11-01T23:00:57.000Z","updatedAt":"2024-11-01T23:00:57.000Z"}},{"id":153,"title":"New Product R","price":1034,"description":"A description","images":["[\"https://placeimg.com/640/480/any\"]"],"creationAt":"2024-11-02T11:49:21.000Z","updatedAt":"2024-11-02T11:49:21.000Z","category":{"id":1,"name":"Clothes","image":"https://i.imgur.com/QkIa5tT.jpeg","creationAt":"2024-11-01T23:00:57.000Z","updatedAt":"2024-11-01T23:00:57.000Z"}},{"id":154,"title":"New Product R","price":1034,"description":"A description","images":["[\"https://placeimg.com/640/480/any\"]"],"creationAt":"2024-11-02T11:49:22.000Z","updatedAt":"2024-11-02T11:49:22.000Z","category":{"id":1,"name":"Clothes","image":"https://i.imgur.com/QkIa5tT.jpeg","creationAt":"2024-11-01T23:00:57.000Z","updatedAt":"2024-11-01T23:00:57.000Z"}},{"id":155,"title":"New Product","price":10,"description":"A description","images":["[\"https://placeimg.com/640/480/any\"]"],"creationAt":"2024-11-02T11:49:26.000Z","updatedAt":"2024-11-02T11:49:26.000Z","category":{"id":1,"name":"Clothes","image":"https://i.imgur.com/QkIa5tT.jpeg","creationAt":"2024-11-01T23:00:57.000Z","updatedAt":"2024-11-01T23:00:57.000Z"}},{"id":156,"title":"New Product","price":10,"description":"A description","images":["[\"https://placeimg.com/640/480/any\"]"],"creationAt":"2024-11-02T11:55:50.000Z","updatedAt":"2024-11-02T11:55:50.000Z","category":{"id":1,"name":"Clothes","image":"https://i.imgur.com/QkIa5tT.jpeg","creationAt":"2024-11-01T23:00:57.000Z","updatedAt":"2024-11-01T23:00:57.000Z"}},{"id":157,"title":"New Product","price":10,"description":"A description","images":["[\"https://placeimg.com/640/480/any\"]"],"creationAt":"2024-11-02T12:17:47.000Z","updatedAt":"2024-11-02T12:17:47.000Z","category":{"id":1,"name":"Clothes","image":"https://i.imgur.com/QkIa5tT.jpeg","creationAt":"2024-11-01T23:00:57.000Z","updatedAt":"2024-11-01T23:00:57.000Z"}},{"id":158,"title":"New Product R","price":1034,"description":"A description","images":["[\"https://placeimg.com/640/480/any\"]"],"creationAt":"2024-11-02T12:21:21.000Z","updatedAt":"2024-11-02T12:21:21.000Z","category":{"id":1,"name":"Clothes","image":"https://i.imgur.com/QkIa5tT.jpeg","creationAt":"2024-11-01T23:00:57.000Z","updatedAt":"2024-11-01T23:00:57.000Z"}},{"id":159,"title":"New Product R","price":1034,"description":"A description","images":["[\"https://placeimg.com/640/480/any\"]"],"creationAt":"2024-11-02T12:21:21.000Z","updatedAt":"2024-11-02T12:21:21.000Z","category":{"id":1,"name":"Clothes","image":"https://i.imgur.com/QkIa5tT.jpeg","creationAt":"2024-11-01T23:00:57.000Z","updatedAt":"2024-11-01T23:00:57.000Z"}},{"id":160,"title":"New Product R","price":1034,"description":"A description","images":["[\"https://placeimg.com/640/480/any\"]"],"creationAt":"2024-11-02T12:21:22.000Z","updatedAt":"2024-11-02T12:21:22.000Z","category":{"id":1,"name":"Clothes","image":"https://i.imgur.com/QkIa5tT.jpeg","creationAt":"2024-11-01T23:00:57.000Z","updatedAt":"2024-11-01T23:00:57.000Z"}},{"id":161,"title":"New Product R","price":1034,"description":"A description","images":["[\"https://placeimg.com/640/480/any\"]"],"creationAt":"2024-11-02T12:22:22.000Z","updatedAt":"2024-11-02T12:22:22.000Z","category":{"id":1,"name":"Clothes","image":"https://i.imgur.com/QkIa5tT.jpeg","creationAt":"2024-11-01T23:00:57.000Z","updatedAt":"2024-11-01T23:00:57.000Z"}},{"id":162,"title":"New Product R","price":1034,"description":"A description","images":["[\"https://placeimg.com/640/480/any\"]"],"creationAt":"2024-11-02T12:22:23.000Z","updatedAt":"2024-11-02T12:22:23.000Z","category":{"id":1,"name":"Clothes","image":"https://i.imgur.com/QkIa5tT.jpeg","creationAt":"2024-11-01T23:00:57.000Z","updatedAt":"2024-11-01T23:00:57.000Z"}},{"id":163,"title":"New Product R","price":1034,"description":"A description","images":["[\"https://placeimg.com/640/480/any\"]"],"creationAt":"2024-11-02T12:22:24.000Z","updatedAt":"2024-11-02T12:22:24.000Z","category":{"id":1,"name":"Clothes","image":"https://i.imgur.com/QkIa5tT.jpeg","creationAt":"2024-11-01T23:00:57.000Z","updatedAt":"2024-11-01T23:00:57.000Z"}},{"id":164,"title":"New Product R","price":1034,"description":"A description","images":["[\"https://placeimg.com/640/480/any\"]"],"creationAt":"2024-11-02T12:23:25.000Z","updatedAt":"2024-11-02T12:23:25.000Z","category":{"id":1,"name":"Clothes","image":"https://i.imgur.com/QkIa5tT.jpeg","creationAt":"2024-11-01T23:00:57.000Z","updatedAt":"2024-11-01T23:00:57.000Z"}},{"id":165,"title":"New Product R","price":1034,"description":"A description","images":["[\"https://placeimg.com/640/480/any\"]"],"creationAt":"2024-11-02T12:23:45.000Z","updatedAt":"2024-11-02T12:23:45.000Z","category":{"id":1,"name":"Clothes","image":"https://i.imgur.com/QkIa5tT.jpeg","creationAt":"2024-11-01T23:00:57.000Z","updatedAt":"2024-11-01T23:00:57.000Z"}},{"id":166,"title":"New Product R","price":1034,"description":"A description","images":["[\"https://placeimg.com/640/480/any\"]"],"creationAt":"2024-11-02T12:23:45.000Z","updatedAt":"2024-11-02T12:23:45.000Z","category":{"id":1,"name":"Clothes","image":"https://i.imgur.com/QkIa5tT.jpeg","creationAt":"2024-11-01T23:00:57.000Z","updatedAt":"2024-11-01T23:00:57.000Z"}},{"id":167,"title":"New Product R","price":1034,"description":"A description","images":["[\"https://placeimg.com/640/480/any\"]"],"creationAt":"2024-11-02T12:23:46.000Z","updatedAt":"2024-11-02T12:23:46.000Z","category":{"id":1,"name":"Clothes","image":"https://i.imgur.com/QkIa5tT.jpeg","creationAt":"2024-11-01T23:00:57.000Z","updatedAt":"2024-11-01T23:00:57.000Z"}},{"id":168,"title":"New Product R","price":1034,"description":"A description","images":["[\"https://placeimg.com/640/480/any\"]"],"creationAt":"2024-11-02T12:24:53.000Z","updatedAt":"2024-11-02T12:24:53.000Z","category":{"id":1,"name":"Clothes","image":"https://i.imgur.com/QkIa5tT.jpeg","creationAt":"2024-11-01T23:00:57.000Z","updatedAt":"2024-11-01T23:00:57.000Z"}},{"id":169,"title":"New Product R","price":1034,"description":"A description","images":["[\"https://placeimg.com/640/480/any\"]"],"creationAt":"2024-11-02T12:24:54.000Z","updatedAt":"2024-11-02T12:24:54.000Z","category":{"id":1,"name":"Clothes","image":"https://i.imgur.com/QkIa5tT.jpeg","creationAt":"2024-11-01T23:00:57.000Z","updatedAt":"2024-11-01T23:00:57.000Z"}},{"id":170,"title":"New Product R","price":1034,"description":"A description","images":["[\"https://placeimg.com/640/480/any\"]"],"creationAt":"2024-11-02T12:24:55.000Z","updatedAt":"2024-11-02T12:24:55.000Z","category":{"id":1,"name":"Clothes","image":"https://i.imgur.com/QkIa5tT.jpeg","creationAt":"2024-11-01T23:00:57.000Z","updatedAt":"2024-11-01T23:00:57.000Z"}},{"id":171,"title":"New Product R","price":1034,"description":"A description","images":["[\"https://placeimg.com/640/480/any\"]"],"creationAt":"2024-11-02T12:34:02.000Z","updatedAt":"2024-11-02T12:34:02.000Z","category":{"id":1,"name":"Clothes","image":"https://i.imgur.com/QkIa5tT.jpeg","creationAt":"2024-11-01T23:00:57.000Z","updatedAt":"2024-11-01T23:00:57.000Z"}},{"id":172,"title":"New Product R","price":1034,"description":"A description","images":["[\"https://placeimg.com/640/480/any\"]"],"creationAt":"2024-11-02T12:34:03.000Z","updatedAt":"2024-11-02T12:34:03.000Z","category":{"id":1,"name":"Clothes","image":"https://i.imgur.com/QkIa5tT.jpeg","creationAt":"2024-11-01T23:00:57.000Z","updatedAt":"2024-11-01T23:00:57.000Z"}},{"id":173,"title":"New Product R","price":1034,"description":"A description","images":["[\"https://placeimg.com/640/480/any\"]"],"creationAt":"2024-11-02T12:34:04.000Z","updatedAt":"2024-11-02T12:34:04.000Z","category":{"id":1,"name":"Clothes","image":"https://i.imgur.com/QkIa5tT.jpeg","creationAt":"2024-11-01T23:00:57.000Z","updatedAt":"2024-11-01T23:00:57.000Z"}},{"id":174,"title":"New Product R","price":1034,"description":"A description","images":["[\"https://placeimg.com/640/480/any\"]"],"creationAt":"2024-11-02T12:34:22.000Z","updatedAt":"2024-11-02T12:34:22.000Z","category":{"id":1,"name":"Clothes","image":"https://i.imgur.com/QkIa5tT.jpeg","creationAt":"2024-11-01T23:00:57.000Z","updatedAt":"2024-11-01T23:00:57.000Z"}},{"id":175,"title":"New Product R","price":1034,"description":"A description","images":["[\"https://placeimg.com/640/480/any\"]"],"creationAt":"2024-11-02T12:34:23.000Z","updatedAt":"2024-11-02T12:34:23.000Z","category":{"id":1,"name":"Clothes","image":"https://i.imgur.com/QkIa5tT.jpeg","creationAt":"2024-11-01T23:00:57.000Z","updatedAt":"2024-11-01T23:00:57.000Z"}},{"id":176,"title":"New Product R","price":1034,"description":"A description","images":["[\"https://placeimg.com/640/480/any\"]"],"creationAt":"2024-11-02T12:34:24.000Z","updatedAt":"2024-11-02T12:34:24.000Z","category":{"id":1,"name":"Clothes","image":"https://i.imgur.com/QkIa5tT.jpeg","creationAt":"2024-11-01T23:00:57.000Z","updatedAt":"2024-11-01T23:00:57.000Z"}},{"id":177,"title":"New Product","price":10,"description":"A description","images":["[\"https://placeimg.com/640/480/any\"]"],"creationAt":"2024-11-02T12:49:54.000Z","updatedAt":"2024-11-02T12:49:54.000Z","category":{"id":1,"name":"Clothes","image":"https://i.imgur.com/QkIa5tT.jpeg","creationAt":"2024-11-01T23:00:57.000Z","updatedAt":"2024-11-01T23:00:57.000Z"}},{"id":178,"title":"New Product","price":10,"description":"A description","images":["[\"https://placeimg.com/640/480/any\"]"],"creationAt":"2024-11-02T13:10:08.000Z","updatedAt":"2024-11-02T13:10:08.000Z","category":{"id":1,"name":"Clothes","image":"https://i.imgur.com/QkIa5tT.jpeg","creationAt":"2024-11-01T23:00:57.000Z","updatedAt":"2024-11-01T23:00:57.000Z"}},{"id":179,"title":"New Product","price":10,"description":"A description","images":["[\"https://placeimg.com/640/480/any\"]"],"creationAt":"2024-11-02T13:28:00.000Z","updatedAt":"2024-11-02T13:28:00.000Z","category":{"id":1,"name":"Clothes","image":"https://i.imgur.com/QkIa5tT.jpeg","creationAt":"2024-11-01T23:00:57.000Z","updatedAt":"2024-11-01T23:00:57.000Z"}},{"id":180,"title":"New Product","price":10,"description":"A description","images":["[\"https://placeimg.com/640/480/any\"]"],"creationAt":"2024-11-02T13:36:20.000Z","updatedAt":"2024-11-02T13:36:20.000Z","category":{"id":1,"name":"Clothes","image":"https://i.imgur.com/QkIa5tT.jpeg","creationAt":"2024-11-01T23:00:57.000Z","updatedAt":"2024-11-01T23:00:57.000Z"}},{"id":181,"title":"New Product","price":10,"description":"A description","images":["[\"https://placeimg.com/640/480/any\"]"],"creationAt":"2024-11-02T13:42:30.000Z","updatedAt":"2024-11-02T13:42:30.000Z","category":{"id":1,"name":"Clothes","image":"https://i.imgur.com/QkIa5tT.jpeg","creationAt":"2024-11-01T23:00:57.000Z","updatedAt":"2024-11-01T23:00:57.000Z"}},{"id":184,"title":"Hic atque a fugit c","price":804,"description":"Velit maiores adipi","images":["[\"https://placeimg.com/640/480/any\"]"],"creationAt":"2024-11-02T13:57:49.000Z","updatedAt":"2024-11-02T13:57:49.000Z","category":{"id":2,"name":"Electronics","image":"https://i.imgur.com/ZANVnHE.jpeg","creationAt":"2024-11-01T23:00:57.000Z","updatedAt":"2024-11-01T23:00:57.000Z"}},{"id":185,"title":"Id aliqua Aliquip ","price":751,"description":"Deserunt aliqua Vol","images":["[\"https://placeimg.com/640/480/any\"]"],"creationAt":"2024-11-02T14:02:52.000Z","updatedAt":"2024-11-02T14:02:52.000Z","category":{"id":2,"name":"Electronics","image":"https://i.imgur.com/ZANVnHE.jpeg","creationAt":"2024-11-01T23:00:57.000Z","updatedAt":"2024-11-01T23:00:57.000Z"}},{"id":186,"title":"New Product","price":10,"description":"A description","images":["[\"https://placeimg.com/640/480/any\"]"],"creationAt":"2024-11-02T14:07:58.000Z","updatedAt":"2024-11-02T14:07:58.000Z","category":{"id":1,"name":"Clothes","image":"https://i.imgur.com/QkIa5tT.jpeg","creationAt":"2024-11-01T23:00:57.000Z","updatedAt":"2024-11-01T23:00:57.000Z"}},{"id":187,"title":"New Product","price":10,"description":"A description","images":["[\"https://placeimg.com/640/480/any\"]"],"creationAt":"2024-11-02T14:25:11.000Z","updatedAt":"2024-11-02T14:25:11.000Z","category":{"id":1,"name":"Clothes","image":"https://i.imgur.com/QkIa5tT.jpeg","creationAt":"2024-11-01T23:00:57.000Z","updatedAt":"2024-11-01T23:00:57.000Z"}},{"id":188,"title":"New Product","price":10,"description":"A description","images":["[\"https://placeimg.com/640/480/any\"]"],"creationAt":"2024-11-02T14:34:33.000Z","updatedAt":"2024-11-02T14:34:33.000Z","category":{"id":1,"name":"Clothes","image":"https://i.imgur.com/QkIa5tT.jpeg","creationAt":"2024-11-01T23:00:57.000Z","updatedAt":"2024-11-01T23:00:57.000Z"}},{"id":189,"title":"New Product","price":10,"description":"A description","images":["[\"https://placeimg.com/640/480/any\"]"],"creationAt":"2024-11-02T14:40:58.000Z","updatedAt":"2024-11-02T14:40:58.000Z","category":{"id":1,"name":"Clothes","image":"https://i.imgur.com/QkIa5tT.jpeg","creationAt":"2024-11-01T23:00:57.000Z","updatedAt":"2024-11-01T23:00:57.000Z"}},{"id":190,"title":"New Product","price":10,"description":"A description","images":["[\"https://placeimg.com/640/480/any\"]"],"creationAt":"2024-11-02T14:47:29.000Z","updatedAt":"2024-11-02T14:47:29.000Z","category":{"id":1,"name":"Clothes","image":"https://i.imgur.com/QkIa5tT.jpeg","creationAt":"2024-11-01T23:00:57.000Z","updatedAt":"2024-11-01T23:00:57.000Z"}},{"id":191,"title":"Мишки Барни","price":18999,"description":"Вкусные мишки","images":["[\"https://products.com/img123123.jpg\"]"],"creationAt":"2024-11-02T14:49:58.000Z","updatedAt":"2024-11-02T14:49:58.000Z","category":{"id":1,"name":"Clothes","image":"https://i.imgur.com/QkIa5tT.jpeg","creationAt":"2024-11-01T23:00:57.000Z","updatedAt":"2024-11-01T23:00:57.000Z"}},{"id":192,"title":"New Product","price":10,"description":"A description","images":["[\"https://placeimg.com/640/480/any\"]"],"creationAt":"2024-11-02T14:54:05.000Z","updatedAt":"2024-11-02T14:54:05.000Z","category":{"id":1,"name":"Clothes","image":"https://i.imgur.com/QkIa5tT.jpeg","creationAt":"2024-11-01T23:00:57.000Z","updatedAt":"2024-11-01T23:00:57.000Z"}},{"id":193,"title":"New Product","price":10,"description":"A description","images":["[\"https://placeimg.com/640/480/any\"]"],"creationAt":"2024-11-02T15:00:54.000Z","updatedAt":"2024-11-02T15:00:54.000Z","category":{"id":1,"name":"Clothes","image":"https://i.imgur.com/QkIa5tT.jpeg","creationAt":"2024-11-01T23:00:57.000Z","updatedAt":"2024-11-01T23:00:57.000Z"}},{"id":194,"title":"Мишки Барни","price":18999,"description":"Вкусные мишки","images":["[\"https://products.com/img123123.jpg\"]"],"creationAt":"2024-11-02T15:02:23.000Z","updatedAt":"2024-11-02T15:02:23.000Z","category":{"id":1,"name":"Clothes","image":"https://i.imgur.com/QkIa5tT.jpeg","creationAt":"2024-11-01T23:00:57.000Z","updatedAt":"2024-11-01T23:00:57.000Z"}},{"id":195,"title":"Мишки Барни","price":18999,"description":"Вкусные мишки","images":["[\"https://products.com/img123123.jpg\"]"],"creationAt":"2024-11-02T15:03:38.000Z","updatedAt":"2024-11-02T15:03:38.000Z","category":{"id":1,"name":"Clothes","image":"https://i.imgur.com/QkIa5tT.jpeg","creationAt":"2024-11-01T23:00:57.000Z","updatedAt":"2024-11-01T23:00:57.000Z"}},{"id":198,"title":"New Product","price":10,"description":"A description","images":["[\"https://placeimg.com/640/480/any\"]"],"creationAt":"2024-11-02T15:21:39.000Z","updatedAt":"2024-11-02T15:21:39.000Z","category":{"id":1,"name":"Clothes","image":"https://i.imgur.com/QkIa5tT.jpeg","creationAt":"2024-11-01T23:00:57.000Z","updatedAt":"2024-11-01T23:00:57.000Z"}},{"id":199,"title":"New Product","price":10,"description":"A description","images":["[\"https://placeimg.com/640/480/any\"]"],"creationAt":"2024-11-02T15:33:07.000Z","updatedAt":"2024-11-02T15:33:07.000Z","category":{"id":1,"name":"Clothes","image":"https://i.imgur.com/QkIa5tT.jpeg","creationAt":"2024-11-01T23:00:57.000Z","updatedAt":"2024-11-01T23:00:57.000Z"}},{"id":200,"title":"New Product","price":10,"description":"A description","images":["[\"https://placeimg.com/640/480/any\"]"],"creationAt":"2024-11-02T15:41:04.000Z","updatedAt":"2024-11-02T15:41:04.000Z","category":{"id":1,"name":"Clothes","image":"https://i.imgur.com/QkIa5tT.jpeg","creationAt":"2024-11-01T23:00:57.000Z","updatedAt":"2024-11-01T23:00:57.000Z"}},{"id":201,"title":"New Product","price":10,"description":"A description","images":["[\"https://placeimg.com/640/480/any\"]"],"creationAt":"2024-11-02T15:47:37.000Z","updatedAt":"2024-11-02T15:47:37.000Z","category":{"id":1,"name":"Clothes","image":"https://i.imgur.com/QkIa5tT.jpeg","creationAt":"2024-11-01T23:00:57.000Z","updatedAt":"2024-11-01T23:00:57.000Z"}},{"id":202,"title":"New Product","price":10,"description":"A description","images":["[\"https://placeimg.com/640/480/any\"]"],"creationAt":"2024-11-02T15:54:15.000Z","updatedAt":"2024-11-02T15:54:15.000Z","category":{"id":1,"name":"Clothes","image":"https://i.imgur.com/QkIa5tT.jpeg","creationAt":"2024-11-01T23:00:57.000Z","updatedAt":"2024-11-01T23:00:57.000Z"}},{"id":203,"title":"Мишки Барни","price":18999,"description":"Вкусные мишки","images":["[\"https://products.com/img123123.jpg\"]"],"creationAt":"2024-11-02T16:00:22.000Z","updatedAt":"2024-11-02T16:00:22.000Z","category":{"id":1,"name":"Clothes","image":"https://i.imgur.com/QkIa5tT.jpeg","creationAt":"2024-11-01T23:00:57.000Z","updatedAt":"2024-11-01T23:00:57.000Z"}},{"id":204,"title":"New Product","price":10,"description":"A description","images":["[\"https://placeimg.com/640/480/any\"]"],"creationAt":"2024-11-02T16:07:34.000Z","updatedAt":"2024-11-02T16:07:34.000Z","category":{"id":1,"name":"Clothes","image":"https://i.imgur.com/QkIa5tT.jpeg","creationAt":"2024-11-01T23:00:57.000Z","updatedAt":"2024-11-01T23:00:57.000Z"}},{"id":205,"title":"Numquam molestiae it","price":276,"description":"Odio blanditiis iste","images":["[\"https://placeimg.com/640/480/any\"]"],"creationAt":"2024-11-02T16:30:16.000Z","updatedAt":"2024-11-02T16:30:16.000Z","category":{"id":1,"name":"Clothes","image":"https://i.imgur.com/QkIa5tT.jpeg","creationAt":"2024-11-01T23:00:57.000Z","updatedAt":"2024-11-01T23:00:57.000Z"}},{"id":206,"title":"New Product","price":10,"description":"A description","images":["[\"https://placeimg.com/640/480/any\"]"],"creationAt":"2024-11-02T16:30:39.000Z","updatedAt":"2024-11-02T16:30:39.000Z","category":{"id":1,"name":"Clothes","image":"https://i.imgur.com/QkIa5tT.jpeg","creationAt":"2024-11-01T23:00:57.000Z","updatedAt":"2024-11-01T23:00:57.000Z"}},{"id":207,"title":"Ratione voluptas lab","price":597,"description":"Sequi enim explicabo","images":["[\"https://placeimg.com/640/480/any\"]"],"creationAt":"2024-11-02T16:31:13.000Z","updatedAt":"2024-11-02T16:31:13.000Z","category":{"id":2,"name":"Electronics","image":"https://i.imgur.com/ZANVnHE.jpeg","creationAt":"2024-11-01T23:00:57.000Z","updatedAt":"2024-11-01T23:00:57.000Z"}},{"id":208,"title":"qq","price":746,"description":"qq","images":["[\"https://placeimg.com/640/480/any\"]"],"creationAt":"2024-11-02T16:31:34.000Z","updatedAt":"2024-11-02T16:31:34.000Z","category":{"id":2,"name":"Electronics","image":"https://i.imgur.com/ZANVnHE.jpeg","creationAt":"2024-11-01T23:00:57.000Z","updatedAt":"2024-11-01T23:00:57.000Z"}},{"id":209,"title":"123","price":123,"description":"123","images":["[\"https://placeimg.com/640/480/any\"]"],"creationAt":"2024-11-02T16:31:55.000Z","updatedAt":"2024-11-02T16:31:55.000Z","category":{"id":2,"name":"Electronics","image":"https://i.imgur.com/ZANVnHE.jpeg","creationAt":"2024-11-01T23:00:57.000Z","updatedAt":"2024-11-01T23:00:57.000Z"}},{"id":210,"title":"Sit ea eligendi dol","price":757,"description":"Omnis suscipit corpo","images":["[\"https://placeimg.com/640/480/any\"]"],"creationAt":"2024-11-02T16:34:30.000Z","updatedAt":"2024-11-02T16:34:30.000Z","category":{"id":2,"name":"Electronics","image":"https://i.imgur.com/ZANVnHE.jpeg","creationAt":"2024-11-01T23:00:57.000Z","updatedAt":"2024-11-01T23:00:57.000Z"}},{"id":211,"title":"Nulla amet magnam r","price":786,"description":"Velit ex velit labor","images":["[\"https://placeimg.com/640/480/any\"]"],"creationAt":"2024-11-02T16:38:02.000Z","updatedAt":"2024-11-02T16:38:02.000Z","category":{"id":2,"name":"Electronics","image":"https://i.imgur.com/ZANVnHE.jpeg","creationAt":"2024-11-01T23:00:57.000Z","updatedAt":"2024-11-01T23:00:57.000Z"}},{"id":212,"title":"New Product","price":10,"description":"A description","images":["[\"https://placeimg.com/640/480/any\"]"],"creationAt":"2024-11-02T16:45:03.000Z","updatedAt":"2024-11-02T16:45:03.000Z","category":{"id":1,"name":"Clothes","image":"https://i.imgur.com/QkIa5tT.jpeg","creationAt":"2024-11-01T23:00:57.000Z","updatedAt":"2024-11-01T23:00:57.000Z"}},{"id":213,"title":"Мишки Барни","price":18999,"description":"Вкусные мишки","images":["[\"https://products.com/img123123.jpg\"]"],"creationAt":"2024-11-02T16:48:06.000Z","updatedAt":"2024-11-02T16:48:06.000Z","category":{"id":1,"name":"Clothes","image":"https://i.imgur.com/QkIa5tT.jpeg","creationAt":"2024-11-01T23:00:57.000Z","updatedAt":"2024-11-01T23:00:57.000Z"}},{"id":214,"title":"Мишки Барни","price":18999,"description":"Вкусные мишки","images":["[\"https://products.com/img123123.jpg\"]"],"creationAt":"2024-11-02T16:48:34.000Z","updatedAt":"2024-11-02T16:48:34.000Z","category":{"id":1,"name":"Clothes","image":"https://i.imgur.com/QkIa5tT.jpeg","creationAt":"2024-11-01T23:00:57.000Z","updatedAt":"2024-11-01T23:00:57.000Z"}},{"id":215,"title":"Мишки Барни","price":18999,"description":"Вкусные мишки","images":["[\"https://products.com/img123123.jpg\"]"],"creationAt":"2024-11-02T16:48:36.000Z","updatedAt":"2024-11-02T16:48:36.000Z","category":{"id":1,"name":"Clothes","image":"https://i.imgur.com/QkIa5tT.jpeg","creationAt":"2024-11-01T23:00:57.000Z","updatedAt":"2024-11-01T23:00:57.000Z"}},{"id":216,"title":"Мишки Барни","price":18999,"description":"Вкусные мишки","images":["[\"https://products.com/img123123.jpg\"]"],"creationAt":"2024-11-02T16:48:38.000Z","updatedAt":"2024-11-02T16:48:38.000Z","category":{"id":1,"name":"Clothes","image":"https://i.imgur.com/QkIa5tT.jpeg","creationAt":"2024-11-01T23:00:57.000Z","updatedAt":"2024-11-01T23:00:57.000Z"}},{"id":217,"title":"New Product","price":10,"description":"A description","images":["[\"https://placeimg.com/640/480/any\"]"],"creationAt":"2024-11-02T16:51:29.000Z","updatedAt":"2024-11-02T16:51:29.000Z","category":{"id":1,"name":"Clothes","image":"https://i.imgur.com/QkIa5tT.jpeg","creationAt":"2024-11-01T23:00:57.000Z","updatedAt":"2024-11-01T23:00:57.000Z"}},{"id":218,"title":"New Product","price":10,"description":"A description","images":["[\"https://placeimg.com/640/480/any\"]"],"creationAt":"2024-11-02T16:57:48.000Z","updatedAt":"2024-11-02T16:57:48.000Z","category":{"id":1,"name":"Clothes","image":"https://i.imgur.com/QkIa5tT.jpeg","creationAt":"2024-11-01T23:00:57.000Z","updatedAt":"2024-11-01T23:00:57.000Z"}},{"id":219,"title":"New Product","price":10,"description":"A description","images":["[\"https://placeimg.com/640/480/any\"]"],"creationAt":"2024-11-02T17:11:44.000Z","updatedAt":"2024-11-02T17:11:44.000Z","category":{"id":1,"name":"Clothes","image":"https://i.imgur.com/QkIa5tT.jpeg","creationAt":"2024-11-01T23:00:57.000Z","updatedAt":"2024-11-01T23:00:57.000Z"}},{"id":220,"title":"New Product","price":10,"description":"A description","images":["[\"https://placeimg.com/640/480/any\"]"],"creationAt":"2024-11-02T17:27:02.000Z","updatedAt":"2024-11-02T17:27:02.000Z","category":{"id":1,"name":"Clothes","image":"https://i.imgur.com/QkIa5tT.jpeg","creationAt":"2024-11-01T23:00:57.000Z","updatedAt":"2024-11-01T23:00:57.000Z"}},{"id":221,"title":"New Product","price":10,"description":"A description","images":["[\"https://placeimg.com/640/480/any\"]"],"creationAt":"2024-11-02T17:34:55.000Z","updatedAt":"2024-11-02T17:34:55.000Z","category":{"id":1,"name":"Clothes","image":"https://i.imgur.com/QkIa5tT.jpeg","creationAt":"2024-11-01T23:00:57.000Z","updatedAt":"2024-11-01T23:00:57.000Z"}},{"id":223,"title":"Classic White Tee - Timeless Style and Comfort","price":65,"description":"Camiseta branca básica, com estilo atemporal e conforto para qualquer ocasião.","images":["[\"https://example.com/camiseta_branca_conforto.jpg\"]"],"creationAt":"2024-11-02T17:37:24.000Z","updatedAt":"2024-11-02T17:37:24.000Z","category":{"id":1,"name":"Clothes","image":"https://i.imgur.com/QkIa5tT.jpeg","creationAt":"2024-11-01T23:00:57.000Z","updatedAt":"2024-11-01T23:00:57.000Z"}},{"id":224,"title":"Classic Black T-Shirt","price":31,"description":"Camiseta preta básica com design clássico, ideal para uso diário.","images":["[\"https://example.com/camiseta_preta.jpg\"]"],"creationAt":"2024-11-02T17:37:24.000Z","updatedAt":"2024-11-02T17:37:24.000Z","category":{"id":1,"name":"Clothes","image":"https://i.imgur.com/QkIa5tT.jpeg","creationAt":"2024-11-01T23:00:57.000Z","updatedAt":"2024-11-01T23:00:57.000Z"}},{"id":225,"title":"Sleek Wireless Headphone & Inked Earbud Set","price":41,"description":"Fone de ouvido sem fio com design elegante e fones de ouvido intra-auriculares inclusos.","images":["[\"https://example.com/fone_sleek.jpg\"]"],"creationAt":"2024-11-02T17:37:25.000Z","updatedAt":"2024-11-02T17:37:25.000Z","category":{"id":2,"name":"Electronics","image":"https://i.imgur.com/ZANVnHE.jpeg","creationAt":"2024-11-01T23:00:57.000Z","updatedAt":"2024-11-01T23:00:57.000Z"}},{"id":226,"title":"Sleek Comfort-Fit Over-Ear Headphones","price":25,"description":"Fones de ouvido confortáveis, com excelente qualidade de som e ajuste ergonômico.","images":["[\"https://example.com/fone_conforto.jpg\"]"],"creationAt":"2024-11-02T17:37:25.000Z","updatedAt":"2024-11-02T17:37:25.000Z","category":{"id":2,"name":"Electronics","image":"https://i.imgur.com/ZANVnHE.jpeg","creationAt":"2024-11-01T23:00:57.000Z","updatedAt":"2024-11-01T23:00:57.000Z"}},{"id":227,"title":"New Product","price":10,"description":"A description","images":["[\"https://placeimg.com/640/480/any\"]"],"creationAt":"2024-11-02T17:41:24.000Z","updatedAt":"2024-11-02T17:41:24.000Z","category":{"id":1,"name":"Clothes","image":"https://i.imgur.com/QkIa5tT.jpeg","creationAt":"2024-11-01T23:00:57.000Z","updatedAt":"2024-11-01T23:00:57.000Z"}},{"id":228,"title":"New Product","price":10,"description":"A description","images":["[\"https://placeimg.com/640/480/any\"]"],"creationAt":"2024-11-02T17:47:45.000Z","updatedAt":"2024-11-02T17:47:45.000Z","category":{"id":1,"name":"Clothes","image":"https://i.imgur.com/QkIa5tT.jpeg","creationAt":"2024-11-01T23:00:57.000Z","updatedAt":"2024-11-01T23:00:57.000Z"}},{"id":229,"title":"New Product","price":10,"description":"A description","images":["[\"https://placeimg.com/640/480/any\"]"],"creationAt":"2024-11-02T17:54:13.000Z","updatedAt":"2024-11-02T17:54:13.000Z","category":{"id":1,"name":"Clothes","image":"https://i.imgur.com/QkIa5tT.jpeg","creationAt":"2024-11-01T23:00:57.000Z","updatedAt":"2024-11-01T23:00:57.000Z"}},{"id":230,"title":"X-box 360","price":1000,"description":"Um videogame","images":["[\"https://example.com/xbox360.jpg\"]"],"creationAt":"2024-11-02T17:54:26.000Z","updatedAt":"2024-11-02T17:54:26.000Z","category":{"id":7,"name":"New Category","image":"https://placeimg.com/640/480/any","creationAt":"2024-11-01T23:24:43.000Z","updatedAt":"2024-11-01T23:24:43.000Z"}},{"id":231,"title":"X-box 360","price":1000,"description":"Um videogame","images":["[\"https://example.com/xbox360.jpg\"]"],"creationAt":"2024-11-02T17:57:26.000Z","updatedAt":"2024-11-02T17:57:26.000Z","category":{"id":7,"name":"New Category","image":"https://placeimg.com/640/480/any","creationAt":"2024-11-01T23:24:43.000Z","updatedAt":"2024-11-01T23:24:43.000Z"}},{"id":232,"title":"New Product","price":10,"description":"A description","images":["[\"https://placeimg.com/640/480/any\"]"],"creationAt":"2024-11-02T18:00:47.000Z","updatedAt":"2024-11-02T18:00:47.000Z","category":{"id":1,"name":"Clothes","image":"https://i.imgur.com/QkIa5tT.jpeg","creationAt":"2024-11-01T23:00:57.000Z","updatedAt":"2024-11-01T23:00:57.000Z"}}]